htmlipi/__init__.py
htmlipi/renderer.py
htmlipi/tag.py
htmlipi/utils.py
htmlipi-1.0.0.dist-info/METADATA
htmlipi-1.0.0.dist-info/WHEEL
htmlipi-1.0.0.dist-info/licenses/LICENSE
htmlipi-1.0.0.dist-info/RECORD
